directory_browser_mcp/__init__.py
directory_browser_mcp/__main__.py
directory_browser_mcp/directory_ops.py
directory_browser_mcp/security.py
directory_browser_mcp/server.py
directory_browser_mcp-0.1.5.dist-info/licenses/LICENSE
directory_browser_mcp-0.1.5.dist-info/METADATA
directory_browser_mcp-0.1.5.dist-info/WHEEL
directory_browser_mcp-0.1.5.dist-info/entry_points.txt
directory_browser_mcp-0.1.5.dist-info/top_level.txt
directory_browser_mcp-0.1.5.dist-info/RECORD
