Metadata-Version: 2.4
Name: directory-browser-mcp
Version: 0.1.5
Summary: A secure MCP server for browsing directories and files with access control
Author-email: Your Name <your.email@example.com>
Maintainer-email: Your Name <your.email@example.com>
License: MIT
Project-URL: Homepage, https://github.com/yourusername/directory-browser-mcp
Project-URL: Repository, https://github.com/yourusername/directory-browser-mcp
Project-URL: Issues, https://github.com/yourusername/directory-browser-mcp/issues
Project-URL: Documentation, https://github.com/yourusername/directory-browser-mcp#readme
Project-URL: Changelog, https://github.com/yourusername/directory-browser-mcp/releases
Keywords: mcp,directory,browser,file,server,model-context-protocol
Classifier: Development Status :: 4 - Beta
Classifier: Intended Audience :: Developers
Classifier: License :: OSI Approved :: MIT License
Classifier: Operating System :: OS Independent
Classifier: Programming Language :: Python :: 3
Classifier: Programming Language :: Python :: 3.10
Classifier: Programming Language :: Python :: 3.11
Classifier: Programming Language :: Python :: 3.12
Classifier: Topic :: Software Development :: Libraries :: Python Modules
Classifier: Topic :: System :: Filesystems
Classifier: Topic :: Utilities
Requires-Python: >=3.10
License-File: LICENSE
Requires-Dist: mcp>=1.0.0
Provides-Extra: dev
Requires-Dist: pytest>=7.0.0; extra == "dev"
Requires-Dist: pytest-asyncio>=0.21.0; extra == "dev"
Requires-Dist: black>=23.0.0; extra == "dev"
Requires-Dist: isort>=5.12.0; extra == "dev"
Requires-Dist: flake8>=6.0.0; extra == "dev"
Requires-Dist: mypy>=1.0.0; extra == "dev"
Dynamic: license-file
